kittykittykitty/__init__.py
kittykittykitty/lulz.py
kittykittykitty-1.0.dist-info/LICENSE
kittykittykitty-1.0.dist-info/METADATA
kittykittykitty-1.0.dist-info/WHEEL
kittykittykitty-1.0.dist-info/entry_points.txt
kittykittykitty-1.0.dist-info/top_level.txt
kittykittykitty-1.0.dist-info/RECORD
